dramkit/__init__.py
dramkit/_pkg_info.py
dramkit/_todo.py
dramkit/const.py
dramkit/cryptotools.py
dramkit/datetimetools.py
dramkit/gentools.py
dramkit/install_check.py
dramkit/iotools.py
dramkit/_tmp/CRR.py
dramkit/_tmp/CtrlPreTS.py
dramkit/_tmp/NPairSum.py
dramkit/_tmp/PIDtest.py
dramkit/_tmp/PIDtest2.py
dramkit/_tmp/VMD.py
dramkit/_tmp/__init__.py
dramkit/_tmp/_dijkstra.py
dramkit/_tmp/_hf_download.py
dramkit/_tmp/cca_test.py
dramkit/_tmp/dtw_test.py
dramkit/_tmp/explore.py
dramkit/_tmp/feature_selection.py
dramkit/_tmp/gini.py
dramkit/_tmp/important_sample.py
dramkit/_tmp/merge_sort.py
dramkit/_tmp/moe.py
dramkit/_tmp/mouse_move.py
dramkit/_tmp/mpc_test1.py
dramkit/_tmp/options_Implied_volatility.py
dramkit/_tmp/pf_test.py
dramkit/_tmp/plot_test.py
dramkit/_tmp/plot_test2.py
dramkit/_tmp/simple_smooth.py
dramkit/_tmp/test_Wrapper.py
dramkit/_tmp/test_async_washs.py
dramkit/_tmp/test_await_timeout.py
dramkit/_tmp/test_backtrader.py
dramkit/_tmp/test_chatgpt_v1.py
dramkit/_tmp/test_code.py
dramkit/_tmp/test_find_peaks.py
dramkit/_tmp/test_get_var_name.py
dramkit/_tmp/test_grading.py
dramkit/_tmp/test_lr.py
dramkit/_tmp/test_maxsort.py
dramkit/_tmp/test_multiprocessing.py
dramkit/_tmp/test_ocr.py
dramkit/_tmp/test_pywechat.py
dramkit/_tmp/test_tree.py
dramkit/_tmp/test_tree2.py
dramkit/_tmp/test_wechat_work.py
dramkit/_tmp/tfDNNCls_test.py
dramkit/_tmp/tmp.py
dramkit/_tmp/tmp_args.py
dramkit/_tmp/transformer_all_in_one.py
dramkit/_tmp/transformer_pytorch.py
dramkit/_tmp/utils_SignalDec.py
dramkit/_tmp/utils_TimeSeries.py
dramkit/_tmp/utils_lottery.py
dramkit/_tmp/utils_sem.py
dramkit/backpacks/__init__.py
dramkit/backpacks/backpack01_float_dy.py
dramkit/backpacks/backpack01_int_dy.py
dramkit/datsci/__init__.py
dramkit/datsci/_grad_down.py
dramkit/datsci/_utils_ann.py
dramkit/datsci/activate_funcs.py
dramkit/datsci/ahp.py
dramkit/datsci/ahp_sim_ri.py
dramkit/datsci/apriori.py
dramkit/datsci/curvature.py
dramkit/datsci/elm_cls.py
dramkit/datsci/elm_reg.py
dramkit-0.5.56.dist-info/LICENSE
dramkit-0.5.56.dist-info/METADATA
dramkit-0.5.56.dist-info/WHEEL
dramkit-0.5.56.dist-info/top_level.txt
dramkit-0.5.56.dist-info/RECORD
