Metadata-Version: 2.1
Name: dramkit
Version: 0.5.56
Summary: DramKit is a toolbox.
Home-page: https://github.com/Genlovy-Hoo/dramkit/
Author: Genlovy Hoo, YueYong Hu
Author-email: genlovhyy@163.com
License: MIT
Platform: any
License-File: LICENSE
Requires-Dist: pycryptodome
Requires-Dist: cryptography
Requires-Dist: tqdm
Requires-Dist: pymysql
Requires-Dist: sqlalchemy
Requires-Dist: beartype
Requires-Dist: matplotlib
Requires-Dist: scikit-learn
Requires-Dist: lightgbm
